windmillcategoryv1/__init__.py
windmillcategoryv1/client/__init__.py
windmillcategoryv1/client/category_api.py
windmillcategoryv1/client/category_client.py
windmill_category-1.0.0.2.dist-info/METADATA
windmill_category-1.0.0.2.dist-info/WHEEL
windmill_category-1.0.0.2.dist-info/top_level.txt
windmill_category-1.0.0.2.dist-info/RECORD
