Metadata-Version: 2.1
Name: windmill-category
Version: 1.0.0.2
Summary: sdk in python for windmill category
Home-page: https://console.cloud.baidu-int.com/devops/icode/repos/baidu/themis/category-go/tree/master/sdk/python
Author: zhangzhijun06
Author-email: zhangzhijun06@baidu.com
License: MIT
Classifier: Programming Language :: Python
Classifier: Programming Language :: Python :: 3
Classifier: Programming Language :: Python :: 3.7
Classifier: Programming Language :: Python :: 3.8
Classifier: Programming Language :: Python :: 3.9
Requires-Python: >=3.6
Requires-Dist: bce-python-sdk ==0.8.87
Requires-Dist: bce-internal-sdk
Requires-Dist: pydantic
